pyRAPL/__init__.py
pyRAPL/device.py
pyRAPL/device_api.py
pyRAPL/exception.py
pyRAPL/measurement.py
pyRAPL/pyRAPL.py
pyRAPL/result.py
pyRAPL/sensor.py
pyRAPL/outputs/__init__.py
pyRAPL/outputs/buffered_output.py
pyRAPL/outputs/csvoutput.py
pyRAPL/outputs/dataframeoutput.py
pyRAPL/outputs/mongooutput.py
pyRAPL/outputs/output.py
pyRAPL/outputs/printoutput.py
tests/__init__.py
tests/utils.py
pyRAPL-0.2.3.dist-info/LICENSE
pyRAPL-0.2.3.dist-info/METADATA
pyRAPL-0.2.3.dist-info/WHEEL
pyRAPL-0.2.3.dist-info/top_level.txt
pyRAPL-0.2.3.dist-info/RECORD
