Metadata-Version: 2.1
Name: pyRAPL
Version: 0.2.3
Summary: UNKNOWN
Home-page: UNKNOWN
Author: Chakib Belgaid, Arthur d'Azémar, Guillaume Fieni, Romain Rouvoy
Author-email: powerapi-staff@inria.fr
License: MIT License
Project-URL: Homepage, http://powerapi.org/
Project-URL: Source, https://github.com/powerapi-ng/pyRAPL
Keywords: energy
Platform: linux
Classifier: Programming Language :: Python :: 3.7
Classifier: License :: OSI Approved :: MIT License
Requires-Python: >=3.7
Requires-Dist: psutil (>=5.0.0)
Provides-Extra: docs
Requires-Dist: sphinx (>=1.8.1) ; extra == 'docs'
Requires-Dist: sphinx-autodoc-typehints (>=1.6.0) ; extra == 'docs'
Provides-Extra: mongodb
Requires-Dist: pymongo (>=3.9.0) ; extra == 'mongodb'
Provides-Extra: pandas
Requires-Dist: pandas (>=0.25.1) ; extra == 'pandas'
